from_dict/__init__.py
from_dict/_from_dict.py
from_dict-0.5.0.dist-info/LICENSE
from_dict-0.5.0.dist-info/METADATA
from_dict-0.5.0.dist-info/WHEEL
from_dict-0.5.0.dist-info/top_level.txt
from_dict-0.5.0.dist-info/RECORD
